ReQBodyMan/ReQBodyMan.py
ReQBodyMan/__init__.py
ReQBodyMan-1.4.1.dist-info/LICENSE
ReQBodyMan-1.4.1.dist-info/METADATA
ReQBodyMan-1.4.1.dist-info/WHEEL
ReQBodyMan-1.4.1.dist-info/top_level.txt
ReQBodyMan-1.4.1.dist-info/RECORD
