Metadata-Version: 2.1
Name: ReQBodyMan
Version: 1.4.1
Summary: ReQBodyMan to easily manage body data received with Request
Author-email: Murat Bilginer <mbilginer@brainytech.net>
Project-URL: Homepage, https://github.com/MuratBilginerSoft/ReQBodyMan
Project-URL: Bug Tracker, https://github.com/MuratBilginerSoft/ReQBodyMan/issues
Classifier: Programming Language :: Python :: 3
Classifier: License :: OSI Approved :: MIT License
Classifier: Operating System :: OS Independent
Requires-Python: >=3.7
License-File: LICENSE
